[
    {
        "CategoryId": "10",
        "CategoryName": "Announcements"
    },
    {
        "CategoryId": "12",
        "CategoryName": "Charity - Donate - NGO"
    },
    {
        "CategoryId": "31",
        "CategoryName": "Houses - Apartments for Sale"
    },
    {
        "CategoryId": "32",
        "CategoryName": "Houses - Apartments for Rent"
    },
    {
        "CategoryId": "33",
        "CategoryName": "Commercial Property for Sale"
    },
    {
        "CategoryId": "51",
        "CategoryName": "TV - DVD - Multimedia"
    },
    {
        "CategoryId": "52",
        "CategoryName": "Books - Magazines"
    },
    {
        "CategoryId": "53",
        "CategoryName": "Sport - Fitness Equipment"
    },
    {
        "CategoryId": "54",
        "CategoryName": "Household"
    },
    {
        "CategoryId": "55",
        "CategoryName": "Music - Movies"
    },
    {
        "CategoryId": "56",
        "CategoryName": "Home - Office Furniture"
    },
    {
        "CategoryId": "57",
        "CategoryName": "Toys - Games"
    },
    {
        "CategoryId": "71",
        "CategoryName": "Cars"
    },
    {
        "CategoryId": "72",
        "CategoryName": "Bikes & Scooters"
    },
    {
        "CategoryId": "74",
        "CategoryName": "Spare Parts - Accessories"
    },
    {
        "CategoryId": "91",
        "CategoryName": "Driving Schools"
    },
    {
        "CategoryId": "92",
        "CategoryName": "Motor Service - Repair"
    },
    {
        "CategoryId": "104",
        "CategoryName": "Retail"
    },
    {
        "CategoryId": "110",
        "CategoryName": "Car Pool - Bike Ride"
    },
    {
        "CategoryId": "111",
        "CategoryName": "Home - Kitchen Appliances"
    },
    {
        "CategoryId": "112",
        "CategoryName": "Cameras - Digicams"
    },
    {
        "CategoryId": "113",
        "CategoryName": "Tools - Machinery - Industrial"
    },
    {
        "CategoryId": "114",
        "CategoryName": "Paying Guest - Hostel"
    },
    {
        "CategoryId": "115",
        "CategoryName": "Vacation Rentals - Timeshare"
    },
    {
        "CategoryId": "120",
        "CategoryName": "Lost - Found"
    },
    {
        "CategoryId": "121",
        "CategoryName": "Barter - Exchange"
    },
    {
        "CategoryId": "124",
        "CategoryName": "Astrology - Numerology"
    },
    {
        "CategoryId": "125",
        "CategoryName": "Advertising - Design"
    },
    {
        "CategoryId": "126",
        "CategoryName": "Business Offers"
    },
    {
        "CategoryId": "127",
        "CategoryName": "Catering -Tiffin Services"
    },
    {
        "CategoryId": "128",
        "CategoryName": "Maids & Housekeeping"
    },
    {
        "CategoryId": "129",
        "CategoryName": "Event -Party Planners - DJ"
    },
    {
        "CategoryId": "130",
        "CategoryName": "Loans - Insurance"
    },
    {
        "CategoryId": "131",
        "CategoryName": "Household Repair"
    },
    {
        "CategoryId": "133",
        "CategoryName": "Movers & Packers"
    },
    {
        "CategoryId": "136",
        "CategoryName": "Hotels - Resorts"
    },
    {
        "CategoryId": "138",
        "CategoryName": "Flatmates"
    },
    {
        "CategoryId": "139",
        "CategoryName": "Commercial Vehicles"
    },
    {
        "CategoryId": "144",
        "CategoryName": "Events"
    },
    {
        "CategoryId": "145",
        "CategoryName": "Clothing - Garments"
    },
    {
        "CategoryId": "146",
        "CategoryName": "Antiques - Handicrafts"
    },
    {
        "CategoryId": "147",
        "CategoryName": "Laptops - Computers"
    },
    {
        "CategoryId": "148",
        "CategoryName": "Musical Instruments"
    },
    {
        "CategoryId": "149",
        "CategoryName": "Mobile Phones"
    },
    {
        "CategoryId": "152",
        "CategoryName": "Pet Care - Accessories"
    },
    {
        "CategoryId": "153",
        "CategoryName": "Computer Repair and Service"
    },
    {
        "CategoryId": "154",
        "CategoryName": "Health - Fitness"
    },
    {
        "CategoryId": "162",
        "CategoryName": "Brides"
    },
    {
        "CategoryId": "163",
        "CategoryName": "Grooms"
    },
    {
        "CategoryId": "166",
        "CategoryName": "Pet Adoption"
    },
    {
        "CategoryId": "167",
        "CategoryName": "Gifts - Stationary"
    },
    {
        "CategoryId": "168",
        "CategoryName": "Jewellery"
    },
    {
        "CategoryId": "169",
        "CategoryName": "Collectibles"
    },
    {
        "CategoryId": "170",
        "CategoryName": "Baby - Infant Products"
    },
    {
        "CategoryId": "171",
        "CategoryName": "Home Decor - Furnishings"
    },
    {
        "CategoryId": "172",
        "CategoryName": "Restaurants - Coffee Shops"
    },
    {
        "CategoryId": "173",
        "CategoryName": "Parlours and Salons"
    },
    {
        "CategoryId": "174",
        "CategoryName": "Interior Design"
    },
    {
        "CategoryId": "195",
        "CategoryName": "Career Counseling"
    },
    {
        "CategoryId": "196",
        "CategoryName": "Coaching & Tuitions"
    },
    {
        "CategoryId": "197",
        "CategoryName": "Dance - Music Classes"
    },
    {
        "CategoryId": "198",
        "CategoryName": "Distance Learning Courses"
    },
    {
        "CategoryId": "199",
        "CategoryName": "Professional & Short Term Courses"
    },
    {
        "CategoryId": "201",
        "CategoryName": "Camera Accessories"
    },
    {
        "CategoryId": "202",
        "CategoryName": "Watches"
    },
    {
        "CategoryId": "203",
        "CategoryName": "Fashion Accessories"
    },
    {
        "CategoryId": "204",
        "CategoryName": "Coins - Stamps"
    },
    {
        "CategoryId": "205",
        "CategoryName": "Video Games - Consoles"
    },
    {
        "CategoryId": "206",
        "CategoryName": "Paintings"
    },
    {
        "CategoryId": "207",
        "CategoryName": "Bags - Luggage"
    },
    {
        "CategoryId": "208",
        "CategoryName": "Discounted - Sale Items"
    },
    {
        "CategoryId": "209",
        "CategoryName": "Wholesale - Bulk"
    },
    {
        "CategoryId": "210",
        "CategoryName": "Health - Beauty Products"
    },
    {
        "CategoryId": "211",
        "CategoryName": "Security Equipment - Products"
    },
    {
        "CategoryId": "212",
        "CategoryName": "Accessories"
    },
    {
        "CategoryId": "213",
        "CategoryName": "Computer Peripherals"
    },
    {
        "CategoryId": "214",
        "CategoryName": "Office Supplies"
    },
    {
        "CategoryId": "215",
        "CategoryName": "Commercial Property for Rent"
    },
    {
        "CategoryId": "216",
        "CategoryName": "Service Apartments"
    },
    {
        "CategoryId": "217",
        "CategoryName": "Land - Plot For Sale"
    },
    {
        "CategoryId": "223",
        "CategoryName": "Music Systems - Home Theatre"
    },
    {
        "CategoryId": "224",
        "CategoryName": "Wedding Planners"
    },
    {
        "CategoryId": "225",
        "CategoryName": "Airline - Train - Bus Tickets"
    },
    {
        "CategoryId": "226",
        "CategoryName": "Vacation - Tour Packages"
    },
    {
        "CategoryId": "227",
        "CategoryName": "Travel Agents"
    },
    {
        "CategoryId": "228",
        "CategoryName": "Vehicle Rentals - Taxi Services"
    },
    {
        "CategoryId": "229",
        "CategoryName": "Taxation - Audit"
    },
    {
        "CategoryId": "230",
        "CategoryName": "Investment - Financial Planning"
    },
    {
        "CategoryId": "231",
        "CategoryName": "Vaastu"
    },
    {
        "CategoryId": "232",
        "CategoryName": "Electronics - Appliances Repair"
    },
    {
        "CategoryId": "233",
        "CategoryName": "Carpenters - Furniture Work"
    },
    {
        "CategoryId": "234",
        "CategoryName": "Plumbers - Electricians"
    },
    {
        "CategoryId": "236",
        "CategoryName": "Other Vehicles"
    },
    {
        "CategoryId": "237",
        "CategoryName": "Tender Notices"
    },
    {
        "CategoryId": "238",
        "CategoryName": "Hobby Classes"
    },
    {
        "CategoryId": "239",
        "CategoryName": "Lawyers - Advocates"
    },
    {
        "CategoryId": "241",
        "CategoryName": "Workshops"
    },
    {
        "CategoryId": "242",
        "CategoryName": "Play Schools - Creche"
    },
    {
        "CategoryId": "250",
        "CategoryName": "Pets"
    },
    {
        "CategoryId": "252",
        "CategoryName": "Pet Foods"
    },
    {
        "CategoryId": "253",
        "CategoryName": "Pet Training & Grooming"
    },
    {
        "CategoryId": "254",
        "CategoryName": "Pet Clinics"
    },
    {
        "CategoryId": "255",
        "CategoryName": "Text books & Study Material"
    },
    {
        "CategoryId": "259",
        "CategoryName": "Baby Sitters - Nanny"
    },
    {
        "CategoryId": "260",
        "CategoryName": "Bicycles"
    },
    {
        "CategoryId": "261",
        "CategoryName": "Cooks"
    },
    {
        "CategoryId": "262",
        "CategoryName": "Drivers"
    },
    {
        "CategoryId": "263",
        "CategoryName": "Courier Services"
    },
    {
        "CategoryId": "264",
        "CategoryName": "Retail"
    },
    {
        "CategoryId": "266",
        "CategoryName": "Doctors"
    },
    {
        "CategoryId": "267",
        "CategoryName": "DTH & Set Top Boxes"
    },
    {
        "CategoryId": "270",
        "CategoryName": "Villas/Bungalows for Rent"
    },
    {
        "CategoryId": "271",
        "CategoryName": "Villas/Bungalows for Sale"
    },
    {
        "CategoryId": "272",
        "CategoryName": "Full Time Jobs"
    },
    {
        "CategoryId": "273",
        "CategoryName": "Part Time Jobs"
    },
    {
        "CategoryId": "280",
        "CategoryName": "Tablets"
    },
    {
        "CategoryId": "281",
        "CategoryName": "Events"
    },
    {
        "CategoryId": "282",
        "CategoryName": "Pest Control"
    },
    {
        "CategoryId": "284",
        "CategoryName": "Internet/Broadband"
    },
    {
        "CategoryId": "285",
        "CategoryName": "Architect"
    }
]
